vae3d2d/__init__.py
vae3d2d/dataloaders.py
vae3d2d/eval_3d.py
vae3d2d/evaluation.py
vae3d2d/feasibility.py
vae3d2d/image_utils.py
vae3d2d/latent_utils.py
vae3d2d/logger_utils.py
vae3d2d/loss_functions.py
vae3d2d/main.py
vae3d2d/model.py
vae3d2d/train_3d.py
vae3d2d/trainer.py
vae3d2d/model_utils/__init__.py
vae3d2d/model_utils/utils2.py
vae3d2d/model_utils/blocks/__init__.py
vae3d2d/model_utils/blocks/acti_norm.py
vae3d2d/model_utils/blocks/attention_module.py
vae3d2d/model_utils/blocks/convolutions.py
vae3d2d/model_utils/blocks/segresnet_block.py
vae3d2d/model_utils/blocks/upsample.py
vae3d2d/model_utils/blocks/upsample_new.py
vae3d2d/model_utils/layers/__init__.py
vae3d2d/model_utils/layers/convutils.py
vae3d2d/model_utils/layers/factories.py
vae3d2d/model_utils/layers/utils.py
vae3d2d/model_utils/utils/__init__.py
vae3d2d/model_utils/utils/component_store.py
vae3d2d/model_utils/utils/enums.py
vae3d2d/model_utils/utils/misc.py
vae3d2d/model_utils/utils/module.py
vae3d2d/model_utils/utils/type_definitions.py
vae3d2d-0.2.0.dist-info/licenses/LICENSE
vae3d2d-0.2.0.dist-info/METADATA
vae3d2d-0.2.0.dist-info/WHEEL
vae3d2d-0.2.0.dist-info/top_level.txt
vae3d2d-0.2.0.dist-info/RECORD
