Metadata-Version: 2.4
Name: vae3d2d
Version: 0.2.0
Summary: 3D and 2D VAE tools for medical and grayscale images
Author-email: Zack Duitz <iduitz@gmail.com>
License: Apache-2.0
Project-URL: Homepage, https://github.com/zackdui/3D_variational_auto_encoder
Project-URL: Issues, https://github.com/zackdui/3D_variational_auto_encoder/issues
Requires-Python: >=3.9
License-File: LICENSE
Requires-Dist: numpy
Requires-Dist: wandb
Requires-Dist: tqdm
Requires-Dist: imageio[ffmpeg]
Requires-Dist: pillow
Dynamic: license-file
